havocbot/__init__.py
havocbot/bot.py
havocbot/client.py
havocbot/common.py
havocbot/exceptions.py
havocbot/message.py
havocbot/plugin.py
havocbot/pluginmanager.py
havocbot/singletonmixin.py
havocbot/stasher.py
havocbot/user.py
havocbot/clients/__init__.py
havocbot/clients/hipchat.py
havocbot/clients/skype.py
havocbot/clients/slack.py
havocbot/clients/xmpp.py
havocbot/core/__init__.py
havocbot/core/havocbot_help.py
havocbot/core/havocbot_list.py
havocbot/core/havocbot_reload.py
havocbot/core/havocbot_restart.py
havocbot/core/havocbot_user.py
havocbot-0.2.0.dist-info/DESCRIPTION.rst
havocbot-0.2.0.dist-info/METADATA
havocbot-0.2.0.dist-info/RECORD
havocbot-0.2.0.dist-info/WHEEL
havocbot-0.2.0.dist-info/metadata.json
havocbot-0.2.0.dist-info/top_level.txt
