Metadata-Version: 2.0
Name: havocbot
Version: 0.2.0
Summary: An extensible chat bot that works across any number of chat programs
Home-page: https://github.com/markperdue/havocbot
Author: Mark Perdue
Author-email: markaperdue@gmail.com
License: MIT
Keywords: chat,slack,jabber,xmpp,hipchat
Platform: UNKNOWN
Classifier: Development Status :: 4 - Beta
Classifier: License :: OSI Approved :: MIT License
Classifier: Intended Audience :: Developers
Classifier: Intended Audience :: End Users/Desktop
Classifier: Topic :: Communications :: Chat
Classifier: Natural Language :: English
Classifier: Programming Language :: Python :: 2.6
Classifier: Programming Language :: Python :: 2.7
Classifier: Programming Language :: Python :: 3.0
Requires-Dist: jsonpickle (>=0.9.2)
Requires-Dist: python-dateutil (>=1.4)
Requires-Dist: requests (>=2.6.0)
Requires-Dist: slackclient (>=1.0.0)
Requires-Dist: sleekxmpp (>=1.3.1)
